pib_utils/__init__.py
pib_utils/kinematics.py
pib_utils/pib_DH.py
pib_utils-1.0.dist-info/METADATA
pib_utils-1.0.dist-info/WHEEL
pib_utils-1.0.dist-info/top_level.txt
pib_utils-1.0.dist-info/RECORD
