Metadata-Version: 2.4
Name: pib-utils
Version: 1.0
Summary: Forward & inverse kinematics helpers for isento's pib robot arms
Author-email: "pib.rocks" <team@pib.rocks>
License:                     GNU AFFERO GENERAL PUBLIC LICENSE
Project-URL: Homepage, https://github.com/isento/pib-utils
Project-URL: Issues, https://github.com/isento/pib-utils/issues
Classifier: Programming Language :: Python :: 3
Classifier: License :: OSI Approved :: MIT License
Classifier: Operating System :: OS Independent
Requires-Python: >=3.9
Requires-Dist: roboticstoolbox-python>=1.1.1
Requires-Dist: spatialmath-python>=1.0.3
Requires-Dist: numpy<2.0,>=1.17.4
Provides-Extra: dev
Requires-Dist: pytest; extra == "dev"
Requires-Dist: ruff; extra == "dev"
Requires-Dist: build; extra == "dev"
Requires-Dist: twine; extra == "dev"
